django_weasyprint/__init__.py
django_weasyprint/models.py
django_weasyprint/utils.py
django_weasyprint/views.py
django_weasyprint/tests/__init__.py
django_weasyprint/tests/test_utils.py
django_weasyprint/tests/test_views.py
django_weasyprint-2.3.1.dist-info/LICENSE
django_weasyprint-2.3.1.dist-info/METADATA
django_weasyprint-2.3.1.dist-info/WHEEL
django_weasyprint-2.3.1.dist-info/top_level.txt
django_weasyprint-2.3.1.dist-info/RECORD
