Metadata-Version: 2.1
Name: django-weasyprint
Version: 2.3.1
Summary: Django WeasyPrint CBV
Home-page: https://github.com/fdemmer/django-weasyprint
Download-URL: https://github.com/fdemmer/django-weasyprint/archive/v2.3.1.tar.gz
Author: Florian Demmer
Author-email: fdemmer@gmail.com
License: Apache-2.0
Project-URL: Changelog, https://github.com/fdemmer/django-weasyprint/blob/v2.3.1/CHANGELOG.md
Classifier: Development Status :: 5 - Production/Stable
Classifier: Environment :: Web Environment
Classifier: Framework :: Django
Classifier: Framework :: Django :: 3.2
Classifier: Framework :: Django :: 4.2
Classifier: Framework :: Django :: 5.0
Classifier: Framework :: Django :: 5.1
Classifier: Intended Audience :: Developers
Classifier: License :: OSI Approved :: Apache Software License
Classifier: Operating System :: OS Independent
Classifier: Programming Language :: Python
Classifier: Programming Language :: Python :: 3 :: Only
Classifier: Programming Language :: Python :: 3
Classifier: Programming Language :: Python :: 3.8
Classifier: Programming Language :: Python :: 3.9
Classifier: Programming Language :: Python :: 3.10
Classifier: Programming Language :: Python :: 3.11
Classifier: Programming Language :: Python :: 3.12
Classifier: Programming Language :: Python :: 3.13
Classifier: Topic :: Software Development :: Libraries :: Python Modules
Requires-Python: >=3.8
License-File: LICENSE
Requires-Dist: Django>=3.2
Requires-Dist: WeasyPrint>=59
